<annotation>
	<folder>my-project-name</folder>
	<filename>baijia_02_616.jpg</filename>
	<path>/my-project-name/baijia_02_616.jpg</path>
	<source>
		<database>Unspecified</database>
	</source>
	<size>
		<width>1280</width>
		<height>720</height>
		<depth>3</depth>
	</size>
	<object>
		<name>baijia</name>
		<pose>Unspecified</pose>
		<truncated>0</truncated>
		<difficult>0</difficult>
		<bndbox>
			<xmin>571</xmin>
			<ymin>440</ymin>
			<xmax>1173</xmax>
			<ymax>662</ymax>
		</bndbox>
	</object>
	<object>
		<name>baijia</name>
		<pose>Unspecified</pose>
		<truncated>0</truncated>
		<difficult>0</difficult>
		<bndbox>
			<xmin>124</xmin>
			<ymin>222</ymin>
			<xmax>268</xmax>
			<ymax>613</ymax>
		</bndbox>
	</object>
</annotation>